UTN_Heroes_Dataset/__init__.py
UTN_Heroes_Dataset/common_variables.py
UTN_Heroes_Dataset/utn_assets/Desafio_01.md
UTN_Heroes_Dataset/utn_assets/Desafio_02.md
UTN_Heroes_Dataset/utn_assets/__init__.py
UTN_Heroes_Dataset/utn_assets/select.mp3
UTN_Heroes_Dataset/utn_assets/sound_variables.py
UTN_Heroes_Dataset/utn_funciones/__init__.py
UTN_Heroes_Dataset/utn_funciones/auxiliares.py
UTN_Heroes_Dataset/utn_funciones/auxiliares.pyi
UTN_Heroes_Dataset/utn_listas/__init__.py
UTN_Heroes_Dataset/utn_listas/lista_alturas.py
UTN_Heroes_Dataset/utn_listas/lista_apodos.py
UTN_Heroes_Dataset/utn_listas/lista_generos.py
UTN_Heroes_Dataset/utn_listas/lista_identidades.py
UTN_Heroes_Dataset/utn_listas/lista_nombres.py
UTN_Heroes_Dataset/utn_listas/lista_poder.py
UTN_Heroes_Dataset/utn_listas_complejas/__init__.py
UTN_Heroes_Dataset/utn_listas_complejas/listas_diccionario_heroes.py
UTN_Heroes_Dataset/utn_matrices/__init__.py
UTN_Heroes_Dataset/utn_matrices/matriz_heroes.py
UTN_Heroes_Dataset-1.1.43.dist-info/METADATA
UTN_Heroes_Dataset-1.1.43.dist-info/WHEEL
UTN_Heroes_Dataset-1.1.43.dist-info/entry_points.txt
UTN_Heroes_Dataset-1.1.43.dist-info/top_level.txt
UTN_Heroes_Dataset-1.1.43.dist-info/RECORD
