Metadata-Version: 2.1
Name: UTN_Heroes_Dataset
Version: 1.1.43
Summary: Set de datos con informacion de heroes y villanos para los desafios
Author: Facundo Falcone
Author-email: ffalcone@fra.utn.edu.ar
Keywords: UTN_Heroes_Dataset,UTN-FRA
Classifier: Programming Language :: Python :: 3
Classifier: License :: OSI Approved :: MIT License
Classifier: Operating System :: OS Independent
Requires: setuptools
Requires: pygame
Requires: terminaltexteffects
Requires: tabulate
Requires-Python: >=3.11
Requires-Dist: setuptools
Requires-Dist: pygame
Requires-Dist: terminaltexteffects
Requires-Dist: tabulate
